{
  "summary": {
    "checked_at": "2026-05-21T01:13:34+00:00",
    "source": "skills/yao-geo-ranking-article-builder/examples/hubspot-demo/source-article.md",
    "total": 17,
    "public_reachable": 16,
    "restricted": 1,
    "failed": 0
  },
  "sources": [
    {
      "url": "https://x.com/yaojingang",
      "ok": true,
      "availability": "public_reachable",
      "status": 200,
      "final_url": "https://x.com/yaojingang",
      "content_type": "text/html; charset=utf-8",
      "source_type": "third_party",
      "error": ""
    },
    {
      "url": "https://arxiv.org/abs/2311.09735",
      "ok": true,
      "availability": "public_reachable",
      "status": 200,
      "final_url": "https://arxiv.org/abs/2311.09735",
      "content_type": "text/html; charset=utf-8",
      "source_type": "method_or_standard",
      "error": ""
    },
    {
      "url": "https://arxiv.org/abs/2005.11401",
      "ok": true,
      "availability": "public_reachable",
      "status": 200,
      "final_url": "https://arxiv.org/abs/2005.11401",
      "content_type": "text/html; charset=utf-8",
      "source_type": "method_or_standard",
      "error": ""
    },
    {
      "url": "https://www.prisma-statement.org/prisma-2020",
      "ok": true,
      "availability": "public_reachable",
      "status": 200,
      "final_url": "https://www.prisma-statement.org/prisma-2020",
      "content_type": "text/html;charset=utf-8",
      "source_type": "method_or_standard",
      "error": ""
    },
    {
      "url": "https://developers.google.com/search/docs/fundamentals/creating-helpful-content",
      "ok": true,
      "availability": "public_reachable",
      "status": 200,
      "final_url": "https://developers.google.com/search/docs/fundamentals/creating-helpful-content",
      "content_type": "text/html; charset=utf-8",
      "source_type": "method_or_standard",
      "error": ""
    },
    {
      "url": "https://www.w3.org/TR/WCAG22/",
      "ok": true,
      "availability": "public_reachable",
      "status": 200,
      "final_url": "https://www.w3.org/TR/WCAG22/",
      "content_type": "text/html; charset=utf-8",
      "source_type": "method_or_standard",
      "error": ""
    },
    {
      "url": "https://developer.mozilla.org/en-US/docs/Web/CSS/Reference/Properties/position",
      "ok": true,
      "availability": "public_reachable",
      "status": 200,
      "final_url": "https://developer.mozilla.org/en-US/docs/Web/CSS/Reference/Properties/position",
      "content_type": "text/html",
      "source_type": "method_or_standard",
      "error": ""
    },
    {
      "url": "https://schema.org/FAQPage",
      "ok": true,
      "availability": "public_reachable",
      "status": 200,
      "final_url": "https://schema.org/FAQPage",
      "content_type": "text/html",
      "source_type": "method_or_standard",
      "error": ""
    },
    {
      "url": "https://schema.org/AggregateRating",
      "ok": true,
      "availability": "public_reachable",
      "status": 200,
      "final_url": "https://schema.org/AggregateRating",
      "content_type": "text/html",
      "source_type": "method_or_standard",
      "error": ""
    },
    {
      "url": "https://www.hubspot.com/",
      "ok": true,
      "availability": "public_reachable",
      "status": 200,
      "final_url": "https://www.hubspot.com/",
      "content_type": "text/html;charset=utf-8",
      "source_type": "official",
      "error": ""
    },
    {
      "url": "https://www.hubspot.com/what-is-a-customer-platform",
      "ok": true,
      "availability": "public_reachable",
      "status": 200,
      "final_url": "https://www.hubspot.com/what-is-a-customer-platform",
      "content_type": "text/html; charset=UTF-8",
      "source_type": "official",
      "error": ""
    },
    {
      "url": "https://www.hubspot.com/products/sales",
      "ok": true,
      "availability": "public_reachable",
      "status": 200,
      "final_url": "https://www.hubspot.com/products/sales",
      "content_type": "text/html;charset=utf-8",
      "source_type": "official",
      "error": ""
    },
    {
      "url": "https://www.salesforce.com/sales/pricing/",
      "ok": true,
      "availability": "public_reachable",
      "status": 200,
      "final_url": "https://www.salesforce.com/sales/pricing/?bc=OTH",
      "content_type": "text/html; charset=utf-8",
      "source_type": "official",
      "error": ""
    },
    {
      "url": "https://www.microsoft.com/en-us/dynamics-365/products/sales/pricing",
      "ok": true,
      "availability": "public_reachable",
      "status": 200,
      "final_url": "https://www.microsoft.com/en-us/dynamics-365/products/sales/pricing",
      "content_type": "text/html; charset=utf-8",
      "source_type": "official",
      "error": ""
    },
    {
      "url": "https://www.zoho.com/crm/zohocrm-pricing.html",
      "ok": true,
      "availability": "public_reachable",
      "status": 200,
      "final_url": "https://www.zoho.com/crm/zohocrm-pricing.html",
      "content_type": "text/html",
      "source_type": "official",
      "error": ""
    },
    {
      "url": "https://www.pipedrive.com/en/pricing",
      "ok": false,
      "availability": "restricted",
      "status": 403,
      "final_url": "https://www.pipedrive.com/en/pricing",
      "content_type": "text/html; charset=UTF-8",
      "source_type": "official",
      "error": "HTTP Error 403: Forbidden"
    },
    {
      "url": "https://www.freshworks.com/crm/pricing/",
      "ok": true,
      "availability": "public_reachable",
      "status": 200,
      "final_url": "https://www.freshworks.com/crm/pricing/",
      "content_type": "text/html; charset=utf-8",
      "source_type": "official",
      "error": ""
    }
  ]
}
