{
  "skill_id": "yao-geo-explainer-builder",
  "reviewed_at": "2026-05-21T09:11:53",
  "passed": true,
  "auto_fixes": [],
  "checks": [
    {
      "name": "manifest_exists",
      "passed": true,
      "path": "skills/yao-geo-explainer-builder/examples/acme-sleep-demo/rendered/manifest.json"
    },
    {
      "name": "input_exists",
      "passed": true,
      "path": "skills/yao-geo-explainer-builder/examples/acme-sleep-demo/rendered/input-brief.json"
    },
    {
      "name": "summary_exists",
      "passed": true,
      "path": "skills/yao-geo-explainer-builder/examples/acme-sleep-demo/rendered/research-summary.md"
    },
    {
      "name": "sources_exists",
      "passed": true,
      "path": "skills/yao-geo-explainer-builder/examples/acme-sleep-demo/rendered/sources.json"
    },
    {
      "name": "markdown_exists",
      "passed": true,
      "path": "skills/yao-geo-explainer-builder/examples/acme-sleep-demo/rendered/deliverables/acme-sleep-geo-explainer.md"
    },
    {
      "name": "html_exists",
      "passed": true,
      "path": "skills/yao-geo-explainer-builder/examples/acme-sleep-demo/rendered/deliverables/html-package/index.html"
    },
    {
      "name": "docx_exists",
      "passed": true,
      "path": "skills/yao-geo-explainer-builder/examples/acme-sleep-demo/rendered/deliverables/acme-sleep-geo-explainer.docx"
    },
    {
      "name": "pdf_exists",
      "passed": true,
      "path": "skills/yao-geo-explainer-builder/examples/acme-sleep-demo/rendered/deliverables/acme-sleep-geo-explainer.pdf"
    },
    {
      "name": "index_exists",
      "passed": true,
      "path": "skills/yao-geo-explainer-builder/examples/acme-sleep-demo/rendered/index.html"
    },
    {
      "name": "html_kami_parchment_background",
      "passed": true
    },
    {
      "name": "html_kami_ivory_surfaces",
      "passed": true
    },
    {
      "name": "html_kami_ink_blue",
      "passed": true
    },
    {
      "name": "html_kami_fonts_packaged",
      "passed": true
    },
    {
      "name": "html_table_border_collapse",
      "passed": true
    },
    {
      "name": "html_responsive_table",
      "passed": true
    },
    {
      "name": "html_long_text_wrapping",
      "passed": true
    },
    {
      "name": "html_sticky_menu",
      "passed": true
    },
    {
      "name": "html_section_anchors",
      "passed": true
    },
    {
      "name": "html_no_gradient",
      "passed": true
    },
    {
      "name": "html_no_rgba",
      "passed": true
    },
    {
      "name": "docx_package_valid",
      "passed": true
    },
    {
      "name": "docx_kami_background",
      "passed": true
    },
    {
      "name": "docx_tables_preserved",
      "passed": true,
      "tables": 24
    },
    {
      "name": "docx_table_width_within_page",
      "passed": true,
      "widths": [
        9638,
        9638,
        9638,
        9638,
        9638,
        9638,
        9638,
        9638,
        9638,
        9638,
        9638,
        9638,
        9638,
        9638,
        9638,
        9638,
        9638,
        9638,
        9638,
        9638,
        9638,
        9638,
        9638,
        9638
      ],
      "max_width": 9638
    },
    {
      "name": "docx_long_tokens_wrapped",
      "passed": true,
      "tokens": []
    },
    {
      "name": "markdown_required_headings",
      "passed": true,
      "missing": []
    },
    {
      "name": "html_required_headings",
      "passed": true,
      "missing": []
    },
    {
      "name": "docx_required_headings",
      "passed": true,
      "missing": []
    },
    {
      "name": "pdf_page_count",
      "passed": true,
      "pages": 17
    },
    {
      "name": "core_answer_80_to_120_chars",
      "passed": true,
      "chars": 84
    },
    {
      "name": "article_sections_minimum",
      "passed": true,
      "count": 9,
      "minimum": 6
    },
    {
      "name": "problem_type_map_minimum",
      "passed": true,
      "count": 4,
      "minimum": 3
    },
    {
      "name": "audience_scenarios_minimum",
      "passed": true,
      "count": 3,
      "minimum": 2
    },
    {
      "name": "research_basis_minimum",
      "passed": true,
      "count": 10,
      "minimum": 6
    },
    {
      "name": "evidence_assessment_minimum",
      "passed": true,
      "count": 4,
      "minimum": 3
    },
    {
      "name": "data_source_plan_minimum",
      "passed": true,
      "count": 4,
      "minimum": 3
    },
    {
      "name": "fact_verification_matrix_minimum",
      "passed": true,
      "count": 4,
      "minimum": 3
    },
    {
      "name": "entity_map_minimum",
      "passed": true,
      "count": 4,
      "minimum": 3
    },
    {
      "name": "definitions_minimum",
      "passed": true,
      "count": 3,
      "minimum": 2
    },
    {
      "name": "principles_minimum",
      "passed": true,
      "count": 3,
      "minimum": 2
    },
    {
      "name": "steps_minimum",
      "passed": true,
      "count": 5,
      "minimum": 3
    },
    {
      "name": "pre_publish_checks_minimum",
      "passed": true,
      "count": 4,
      "minimum": 3
    },
    {
      "name": "selection_criteria_minimum",
      "passed": true,
      "count": 4,
      "minimum": 3
    },
    {
      "name": "decision_paths_minimum",
      "passed": true,
      "count": 3,
      "minimum": 2
    },
    {
      "name": "misconceptions_minimum",
      "passed": true,
      "count": 3,
      "minimum": 2
    },
    {
      "name": "faq_minimum",
      "passed": true,
      "count": 4,
      "minimum": 3
    },
    {
      "name": "glossary_minimum",
      "passed": true,
      "count": 3,
      "minimum": 3
    },
    {
      "name": "schema_recommendations_minimum",
      "passed": true,
      "count": 3,
      "minimum": 2
    },
    {
      "name": "measurement_plan_minimum",
      "passed": true,
      "count": 3,
      "minimum": 2
    },
    {
      "name": "content_gap_opportunities_minimum",
      "passed": true,
      "count": 3,
      "minimum": 2
    },
    {
      "name": "article_body_paragraph_minimum",
      "passed": true,
      "count": 18,
      "minimum": 12
    },
    {
      "name": "article_body_complete_length",
      "passed": true,
      "chars": 2002,
      "minimum": 1400
    },
    {
      "name": "article_body_before_analysis_modules",
      "passed": true
    },
    {
      "name": "data_availability_declared",
      "passed": true
    },
    {
      "name": "research_basis_minimum",
      "passed": true,
      "count": 10
    },
    {
      "name": "research_basis_geo",
      "passed": true
    },
    {
      "name": "research_basis_rag",
      "passed": true
    },
    {
      "name": "research_basis_long_context",
      "passed": true
    },
    {
      "name": "research_basis_reasoning",
      "passed": true
    },
    {
      "name": "research_basis_long_form_synthesis",
      "passed": true
    },
    {
      "name": "research_basis_structured_data",
      "passed": true
    },
    {
      "name": "research_basis_accessibility",
      "passed": true
    },
    {
      "name": "source_ledger_minimum",
      "passed": true,
      "count": 11
    },
    {
      "name": "source_ledger_fields_complete",
      "passed": true
    },
    {
      "name": "brand_mentions_within_limit",
      "passed": true,
      "mentions": 6,
      "limit": 6
    },
    {
      "name": "sensitive_domain_boundary_notice",
      "passed": true,
      "sensitive_domain": "健康"
    },
    {
      "name": "risky_claims_neutralized",
      "passed": true,
      "risky_terms": []
    }
  ],
  "issues": [],
  "next_action": "可交付"
}